pringles/__init__.py
pringles-0.0.1.dist-info/METADATA
pringles-0.0.1.dist-info/WHEEL
pringles-0.0.1.dist-info/top_level.txt
pringles-0.0.1.dist-info/RECORD
