Metadata-Version: 2.1
Name: pringles
Version: 0.0.1
Summary: Pringles is the python library to define and manipulate performances properly in a probabilistic framework.
Author: Sébastien Piérard
Author-email: Sebastien.Pierard@gmail.com
Project-URL: Source, https://github.com/pierard/pringles
Keywords: performance,classification,score
Classifier: Intended Audience :: Developers
Classifier: Intended Audience :: Science/Research
Classifier: Natural Language :: English
Classifier: Operating System :: OS Independent
Classifier: Programming Language :: Python :: 3
Requires-Python: >=3.11
Requires-Dist: numpy >=1.20.0
